<?xml version="1.0" encoding="UTF-8"?>

<!-- generated on 2025-11-09 03:33:55 by Eclipse SUMO sumo Version 1.24.0
<sumoConfiguration xmlns:xsi="http://www.w3.org/2001/XMLSchema-instance" xsi:noNamespaceSchemaLocation="http://sumo.dlr.de/xsd/sumoConfiguration.xsd">

    <input>
        <net-file value="Olivarez_traci/network/map.net.xml"/>
        <route-files value="Olivarez_traci/demand/demand.rou.xml"/>
        <additional-files value="Olivarez_traci/additionals/map.poly.xml,Olivarez_traci/ additionals/detectors.add.xml"/>
    </input>

    <time>
        <begin value="0"/>
        <end value="10000"/>
        <step-length value="0.05"/>
    </time>

    <processing>
        <lateral-resolution value="0.1"/>
        <collision.action value="none"/>
        <collision.check-junctions value="false"/>
        <collision.mingap-factor value="0"/>
    </processing>

    <report>
        <no-warnings value="true"/>
    </report>

    <traci_server>
        <remote-port value="49998"/>
    </traci_server>

    <gui_only>
        <delay value="0"/>
    </gui_only>

</sumoConfiguration>
-->

<detector xmlns:xsi="http://www.w3.org/2001/XMLSchema-instance" xsi:noNamespaceSchemaLocation="http://sumo.dlr.de/xsd/det_e2_file.xsd">
   <interval begin="0.00" end="300.00" id="e2_9" sampledSeconds="0.00" nVehEntered="0" nVehLeft="0" nVehSeen="0" meanSpeed="-1.00" meanTimeLoss="-1.00" meanOccupancy="0.00" maxOccupancy="0.00" meanMaxJamLengthInVehicles="0.00" meanMaxJamLengthInMeters="0.00" maxJamLengthInVehicles="0" maxJamLengthInMeters="0.00" jamLengthInVehiclesSum="0" jamLengthInMetersSum="0.00" meanHaltingDuration="0.00" maxHaltingDuration="0.00" haltingDurationSum="0.00" meanIntervalHaltingDuration="0.00" maxIntervalHaltingDuration="0.00" intervalHaltingDurationSum="0.00" startedHalts="0.00" meanVehicleNumber="0.00" maxVehicleNumber="0" />
   <interval begin="300.00" end="600.00" id="e2_9" sampledSeconds="0.00" nVehEntered="0" nVehLeft="0" nVehSeen="0" meanSpeed="-1.00" meanTimeLoss="-1.00" meanOccupancy="0.00" maxOccupancy="0.00" meanMaxJamLengthInVehicles="0.00" meanMaxJamLengthInMeters="0.00" maxJamLengthInVehicles="0" maxJamLengthInMeters="0.00" jamLengthInVehiclesSum="0" jamLengthInMetersSum="0.00" meanHaltingDuration="0.00" maxHaltingDuration="0.00" haltingDurationSum="0.00" meanIntervalHaltingDuration="0.00" maxIntervalHaltingDuration="0.00" intervalHaltingDurationSum="0.00" startedHalts="0.00" meanVehicleNumber="0.00" maxVehicleNumber="0" />
   <interval begin="600.00" end="900.00" id="e2_9" sampledSeconds="0.00" nVehEntered="0" nVehLeft="0" nVehSeen="0" meanSpeed="-1.00" meanTimeLoss="-1.00" meanOccupancy="0.00" maxOccupancy="0.00" meanMaxJamLengthInVehicles="0.00" meanMaxJamLengthInMeters="0.00" maxJamLengthInVehicles="0" maxJamLengthInMeters="0.00" jamLengthInVehiclesSum="0" jamLengthInMetersSum="0.00" meanHaltingDuration="0.00" maxHaltingDuration="0.00" haltingDurationSum="0.00" meanIntervalHaltingDuration="0.00" maxIntervalHaltingDuration="0.00" intervalHaltingDurationSum="0.00" startedHalts="0.00" meanVehicleNumber="0.00" maxVehicleNumber="0" />
   <interval begin="900.00" end="1200.00" id="e2_9" sampledSeconds="0.00" nVehEntered="0" nVehLeft="0" nVehSeen="0" meanSpeed="-1.00" meanTimeLoss="-1.00" meanOccupancy="0.00" maxOccupancy="0.00" meanMaxJamLengthInVehicles="0.00" meanMaxJamLengthInMeters="0.00" maxJamLengthInVehicles="0" maxJamLengthInMeters="0.00" jamLengthInVehiclesSum="0" jamLengthInMetersSum="0.00" meanHaltingDuration="0.00" maxHaltingDuration="0.00" haltingDurationSum="0.00" meanIntervalHaltingDuration="0.00" maxIntervalHaltingDuration="0.00" intervalHaltingDurationSum="0.00" startedHalts="0.00" meanVehicleNumber="0.00" maxVehicleNumber="0" />
   <interval begin="1200.00" end="1500.00" id="e2_9" sampledSeconds="0.00" nVehEntered="0" nVehLeft="0" nVehSeen="0" meanSpeed="-1.00" meanTimeLoss="-1.00" meanOccupancy="0.00" maxOccupancy="0.00" meanMaxJamLengthInVehicles="0.00" meanMaxJamLengthInMeters="0.00" maxJamLengthInVehicles="0" maxJamLengthInMeters="0.00" jamLengthInVehiclesSum="0" jamLengthInMetersSum="0.00" meanHaltingDuration="0.00" maxHaltingDuration="0.00" haltingDurationSum="0.00" meanIntervalHaltingDuration="0.00" maxIntervalHaltingDuration="0.00" intervalHaltingDurationSum="0.00" startedHalts="0.00" meanVehicleNumber="0.00" maxVehicleNumber="0" />
   <interval begin="1500.00" end="1800.00" id="e2_9" sampledSeconds="0.00" nVehEntered="0" nVehLeft="0" nVehSeen="0" meanSpeed="-1.00" meanTimeLoss="-1.00" meanOccupancy="0.00" maxOccupancy="0.00" meanMaxJamLengthInVehicles="0.00" meanMaxJamLengthInMeters="0.00" maxJamLengthInVehicles="0" maxJamLengthInMeters="0.00" jamLengthInVehiclesSum="0" jamLengthInMetersSum="0.00" meanHaltingDuration="0.00" maxHaltingDuration="0.00" haltingDurationSum="0.00" meanIntervalHaltingDuration="0.00" maxIntervalHaltingDuration="0.00" intervalHaltingDurationSum="0.00" startedHalts="0.00" meanVehicleNumber="0.00" maxVehicleNumber="0" />
   <interval begin="1800.00" end="2100.00" id="e2_9" sampledSeconds="0.00" nVehEntered="0" nVehLeft="0" nVehSeen="0" meanSpeed="-1.00" meanTimeLoss="-1.00" meanOccupancy="0.00" maxOccupancy="0.00" meanMaxJamLengthInVehicles="0.00" meanMaxJamLengthInMeters="0.00" maxJamLengthInVehicles="0" maxJamLengthInMeters="0.00" jamLengthInVehiclesSum="0" jamLengthInMetersSum="0.00" meanHaltingDuration="0.00" maxHaltingDuration="0.00" haltingDurationSum="0.00" meanIntervalHaltingDuration="0.00" maxIntervalHaltingDuration="0.00" intervalHaltingDurationSum="0.00" startedHalts="0.00" meanVehicleNumber="0.00" maxVehicleNumber="0" />
   <interval begin="2100.00" end="2400.00" id="e2_9" sampledSeconds="0.00" nVehEntered="0" nVehLeft="0" nVehSeen="0" meanSpeed="-1.00" meanTimeLoss="-1.00" meanOccupancy="0.00" maxOccupancy="0.00" meanMaxJamLengthInVehicles="0.00" meanMaxJamLengthInMeters="0.00" maxJamLengthInVehicles="0" maxJamLengthInMeters="0.00" jamLengthInVehiclesSum="0" jamLengthInMetersSum="0.00" meanHaltingDuration="0.00" maxHaltingDuration="0.00" haltingDurationSum="0.00" meanIntervalHaltingDuration="0.00" maxIntervalHaltingDuration="0.00" intervalHaltingDurationSum="0.00" startedHalts="0.00" meanVehicleNumber="0.00" maxVehicleNumber="0" />
   <interval begin="2400.00" end="2700.00" id="e2_9" sampledSeconds="0.00" nVehEntered="0" nVehLeft="0" nVehSeen="0" meanSpeed="-1.00" meanTimeLoss="-1.00" meanOccupancy="0.00" maxOccupancy="0.00" meanMaxJamLengthInVehicles="0.00" meanMaxJamLengthInMeters="0.00" maxJamLengthInVehicles="0" maxJamLengthInMeters="0.00" jamLengthInVehiclesSum="0" jamLengthInMetersSum="0.00" meanHaltingDuration="0.00" maxHaltingDuration="0.00" haltingDurationSum="0.00" meanIntervalHaltingDuration="0.00" maxIntervalHaltingDuration="0.00" intervalHaltingDurationSum="0.00" startedHalts="0.00" meanVehicleNumber="0.00" maxVehicleNumber="0" />
   <interval begin="2700.00" end="3000.00" id="e2_9" sampledSeconds="0.00" nVehEntered="0" nVehLeft="0" nVehSeen="0" meanSpeed="-1.00" meanTimeLoss="-1.00" meanOccupancy="0.00" maxOccupancy="0.00" meanMaxJamLengthInVehicles="0.00" meanMaxJamLengthInMeters="0.00" maxJamLengthInVehicles="0" maxJamLengthInMeters="0.00" jamLengthInVehiclesSum="0" jamLengthInMetersSum="0.00" meanHaltingDuration="0.00" maxHaltingDuration="0.00" haltingDurationSum="0.00" meanIntervalHaltingDuration="0.00" maxIntervalHaltingDuration="0.00" intervalHaltingDurationSum="0.00" startedHalts="0.00" meanVehicleNumber="0.00" maxVehicleNumber="0" />
   <interval begin="3000.00" end="3300.00" id="e2_9" sampledSeconds="0.00" nVehEntered="0" nVehLeft="0" nVehSeen="0" meanSpeed="-1.00" meanTimeLoss="-1.00" meanOccupancy="0.00" maxOccupancy="0.00" meanMaxJamLengthInVehicles="0.00" meanMaxJamLengthInMeters="0.00" maxJamLengthInVehicles="0" maxJamLengthInMeters="0.00" jamLengthInVehiclesSum="0" jamLengthInMetersSum="0.00" meanHaltingDuration="0.00" maxHaltingDuration="0.00" haltingDurationSum="0.00" meanIntervalHaltingDuration="0.00" maxIntervalHaltingDuration="0.00" intervalHaltingDurationSum="0.00" startedHalts="0.00" meanVehicleNumber="0.00" maxVehicleNumber="0" />
   <interval begin="3300.00" end="3600.00" id="e2_9" sampledSeconds="0.00" nVehEntered="0" nVehLeft="0" nVehSeen="0" meanSpeed="-1.00" meanTimeLoss="-1.00" meanOccupancy="0.00" maxOccupancy="0.00" meanMaxJamLengthInVehicles="0.00" meanMaxJamLengthInMeters="0.00" maxJamLengthInVehicles="0" maxJamLengthInMeters="0.00" jamLengthInVehiclesSum="0" jamLengthInMetersSum="0.00" meanHaltingDuration="0.00" maxHaltingDuration="0.00" haltingDurationSum="0.00" meanIntervalHaltingDuration="0.00" maxIntervalHaltingDuration="0.00" intervalHaltingDurationSum="0.00" startedHalts="0.00" meanVehicleNumber="0.00" maxVehicleNumber="0" />
   <interval begin="3600.00" end="3900.00" id="e2_9" sampledSeconds="822.83" nVehEntered="13" nVehLeft="13" nVehSeen="13" meanSpeed="1.59" meanTimeLoss="59.25" meanOccupancy="12.41" maxOccupancy="23.59" meanMaxJamLengthInVehicles="2.24" meanMaxJamLengthInMeters="13.93" maxJamLengthInVehicles="6" maxJamLengthInMeters="30.28" jamLengthInVehiclesSum="13559" jamLengthInMetersSum="84089.59" meanHaltingDuration="62.56" maxHaltingDuration="129.15" haltingDurationSum="688.15" meanIntervalHaltingDuration="62.56" maxIntervalHaltingDuration="129.15" intervalHaltingDurationSum="688.15" startedHalts="11.00" meanVehicleNumber="2.74" maxVehicleNumber="6" />
   <interval begin="3900.00" end="4200.00" id="e2_9" sampledSeconds="674.13" nVehEntered="15" nVehLeft="10" nVehSeen="15" meanSpeed="1.99" meanTimeLoss="41.56" meanOccupancy="14.29" maxOccupancy="40.08" meanMaxJamLengthInVehicles="1.75" meanMaxJamLengthInMeters="13.87" maxJamLengthInVehicles="5" maxJamLengthInMeters="38.36" jamLengthInVehiclesSum="10492" jamLengthInMetersSum="83191.63" meanHaltingDuration="41.28" maxHaltingDuration="140.60" haltingDurationSum="536.60" meanIntervalHaltingDuration="41.28" maxIntervalHaltingDuration="140.60" intervalHaltingDurationSum="536.60" startedHalts="13.00" meanVehicleNumber="2.25" maxVehicleNumber="7" />
   <interval begin="4200.00" end="4500.00" id="e2_9" sampledSeconds="2354.79" nVehEntered="16" nVehLeft="10" nVehSeen="21" meanSpeed="0.50" meanTimeLoss="109.86" meanOccupancy="47.01" maxOccupancy="60.68" meanMaxJamLengthInVehicles="6.87" meanMaxJamLengthInMeters="63.95" maxJamLengthInVehicles="11" maxJamLengthInMeters="99.46" jamLengthInVehiclesSum="41312" jamLengthInMetersSum="384414.22" meanHaltingDuration="63.46" maxHaltingDuration="131.00" haltingDurationSum="2348.05" meanIntervalHaltingDuration="56.55" maxIntervalHaltingDuration="131.00" intervalHaltingDurationSum="2092.45" startedHalts="35.00" meanVehicleNumber="7.85" maxVehicleNumber="11" />
   <interval begin="4500.00" end="4800.00" id="e2_9" sampledSeconds="3250.08" nVehEntered="11" nVehLeft="11" nVehSeen="22" meanSpeed="0.37" meanTimeLoss="145.43" meanOccupancy="55.50" maxOccupancy="60.71" meanMaxJamLengthInVehicles="9.56" meanMaxJamLengthInMeters="80.94" maxJamLengthInVehicles="13" maxJamLengthInMeters="99.49" jamLengthInVehiclesSum="57922" jamLengthInMetersSum="489310.35" meanHaltingDuration="74.22" maxHaltingDuration="160.70" haltingDurationSum="4082.00" meanIntervalHaltingDuration="53.45" maxIntervalHaltingDuration="113.70" intervalHaltingDurationSum="2939.70" startedHalts="44.00" meanVehicleNumber="10.84" maxVehicleNumber="13" />
   <interval begin="4800.00" end="5100.00" id="e2_9" sampledSeconds="3522.66" nVehEntered="13" nVehLeft="9" nVehSeen="24" meanSpeed="0.32" meanTimeLoss="144.83" meanOccupancy="55.80" maxOccupancy="64.60" meanMaxJamLengthInVehicles="10.65" meanMaxJamLengthInMeters="80.33" maxJamLengthInVehicles="15" maxJamLengthInMeters="99.49" jamLengthInVehiclesSum="64159" jamLengthInMetersSum="483759.73" meanHaltingDuration="92.83" maxHaltingDuration="152.10" haltingDurationSum="4084.60" meanIntervalHaltingDuration="73.69" maxIntervalHaltingDuration="152.10" intervalHaltingDurationSum="3242.15" startedHalts="35.00" meanVehicleNumber="11.74" maxVehicleNumber="15" />
   <interval begin="5100.00" end="5400.00" id="e2_9" sampledSeconds="3784.07" nVehEntered="14" nVehLeft="17" nVehSeen="29" meanSpeed="0.42" meanTimeLoss="128.22" meanOccupancy="56.96" maxOccupancy="66.81" meanMaxJamLengthInVehicles="11.18" meanMaxJamLengthInMeters="81.24" maxJamLengthInVehicles="16" maxJamLengthInMeters="99.49" jamLengthInVehiclesSum="67404" jamLengthInMetersSum="489299.38" meanHaltingDuration="93.88" maxHaltingDuration="177.40" haltingDurationSum="4787.80" meanIntervalHaltingDuration="66.76" maxIntervalHaltingDuration="102.60" intervalHaltingDurationSum="3404.75" startedHalts="36.00" meanVehicleNumber="12.62" maxVehicleNumber="16" />
   <interval begin="5400.00" end="5700.00" id="e2_9" sampledSeconds="3166.91" nVehEntered="18" nVehLeft="19" nVehSeen="30" meanSpeed="0.62" meanTimeLoss="102.84" meanOccupancy="60.76" maxOccupancy="66.71" meanMaxJamLengthInVehicles="8.98" meanMaxJamLengthInMeters="79.32" maxJamLengthInVehicles="12" maxJamLengthInMeters="99.49" jamLengthInVehiclesSum="54220" jamLengthInMetersSum="478508.90" meanHaltingDuration="82.76" maxHaltingDuration="152.10" haltingDurationSum="3889.60" meanIntervalHaltingDuration="58.41" maxIntervalHaltingDuration="144.25" intervalHaltingDurationSum="2745.40" startedHalts="35.00" meanVehicleNumber="10.56" maxVehicleNumber="12" />
   <interval begin="5700.00" end="6000.00" id="e2_9" sampledSeconds="3152.11" nVehEntered="13" nVehLeft="13" nVehSeen="24" meanSpeed="0.44" meanTimeLoss="128.94" meanOccupancy="62.81" maxOccupancy="66.72" meanMaxJamLengthInVehicles="9.19" meanMaxJamLengthInMeters="82.05" maxJamLengthInVehicles="11" maxJamLengthInMeters="99.49" jamLengthInVehiclesSum="55467" jamLengthInMetersSum="495033.11" meanHaltingDuration="63.28" maxHaltingDuration="121.50" haltingDurationSum="3290.65" meanIntervalHaltingDuration="54.11" maxIntervalHaltingDuration="121.50" intervalHaltingDurationSum="2813.85" startedHalts="41.00" meanVehicleNumber="10.51" maxVehicleNumber="11" />
   <interval begin="6000.00" end="6300.00" id="e2_9" sampledSeconds="3044.72" nVehEntered="15" nVehLeft="16" nVehSeen="26" meanSpeed="0.50" meanTimeLoss="114.63" meanOccupancy="62.25" maxOccupancy="66.92" meanMaxJamLengthInVehicles="8.95" meanMaxJamLengthInMeters="84.10" maxJamLengthInVehicles="11" maxJamLengthInMeters="99.49" jamLengthInVehiclesSum="53876" jamLengthInMetersSum="505441.03" meanHaltingDuration="78.43" maxHaltingDuration="172.00" haltingDurationSum="3215.75" meanIntervalHaltingDuration="66.38" maxIntervalHaltingDuration="132.10" intervalHaltingDurationSum="2721.75" startedHalts="30.00" meanVehicleNumber="10.15" maxVehicleNumber="12" />
   <interval begin="6300.00" end="6600.00" id="e2_9" sampledSeconds="3365.93" nVehEntered="15" nVehLeft="15" nVehSeen="25" meanSpeed="0.45" meanTimeLoss="132.11" meanOccupancy="69.11" maxOccupancy="75.26" meanMaxJamLengthInVehicles="9.91" meanMaxJamLengthInMeters="83.36" maxJamLengthInVehicles="13" maxJamLengthInMeters="99.49" jamLengthInVehiclesSum="59730" jamLengthInMetersSum="502029.38" meanHaltingDuration="93.29" maxHaltingDuration="171.70" haltingDurationSum="4291.30" meanIntervalHaltingDuration="65.71" maxIntervalHaltingDuration="156.55" intervalHaltingDurationSum="3022.50" startedHalts="36.00" meanVehicleNumber="11.22" maxVehicleNumber="13" />
   <interval begin="6600.00" end="6900.00" id="e2_9" sampledSeconds="3361.65" nVehEntered="7" nVehLeft="6" nVehSeen="17" meanSpeed="0.21" meanTimeLoss="196.04" meanOccupancy="70.92" maxOccupancy="75.96" meanMaxJamLengthInVehicles="10.40" meanMaxJamLengthInMeters="88.33" maxJamLengthInVehicles="12" maxJamLengthInMeters="99.49" jamLengthInVehiclesSum="62794" jamLengthInMetersSum="532242.12" meanHaltingDuration="98.72" maxHaltingDuration="191.70" haltingDurationSum="3751.20" meanIntervalHaltingDuration="83.31" maxIntervalHaltingDuration="191.70" intervalHaltingDurationSum="3166.00" startedHalts="28.00" meanVehicleNumber="11.21" maxVehicleNumber="12" />
   <interval begin="6900.00" end="7200.00" id="e2_9" sampledSeconds="3456.19" nVehEntered="16" nVehLeft="15" nVehSeen="27" meanSpeed="0.44" meanTimeLoss="125.84" meanOccupancy="59.78" maxOccupancy="66.11" meanMaxJamLengthInVehicles="10.35" meanMaxJamLengthInMeters="83.07" maxJamLengthInVehicles="13" maxJamLengthInMeters="99.49" jamLengthInVehiclesSum="62227" jamLengthInMetersSum="499475.46" meanHaltingDuration="93.11" maxHaltingDuration="146.25" haltingDurationSum="3445.00" meanIntervalHaltingDuration="84.79" maxIntervalHaltingDuration="136.65" intervalHaltingDurationSum="3137.35" startedHalts="26.00" meanVehicleNumber="11.52" maxVehicleNumber="13" />
   <interval begin="7200.00" end="7500.00" id="e2_9" sampledSeconds="3325.74" nVehEntered="13" nVehLeft="14" nVehSeen="25" meanSpeed="0.44" meanTimeLoss="130.70" meanOccupancy="60.22" maxOccupancy="64.70" meanMaxJamLengthInVehicles="10.13" meanMaxJamLengthInMeters="86.24" maxJamLengthInVehicles="12" maxJamLengthInMeters="99.13" jamLengthInVehiclesSum="60887" jamLengthInMetersSum="518057.35" meanHaltingDuration="128.53" maxHaltingDuration="154.00" haltingDurationSum="3213.20" meanIntervalHaltingDuration="122.29" maxIntervalHaltingDuration="142.50" intervalHaltingDurationSum="3057.35" startedHalts="13.00" meanVehicleNumber="11.09" maxVehicleNumber="12" />
   <interval begin="7500.00" end="7800.00" id="e2_9" sampledSeconds="3650.63" nVehEntered="6" nVehLeft="5" nVehSeen="17" meanSpeed="0.15" meanTimeLoss="213.42" meanOccupancy="61.96" maxOccupancy="64.71" meanMaxJamLengthInVehicles="11.45" meanMaxJamLengthInMeters="92.00" maxJamLengthInVehicles="13" maxJamLengthInMeters="99.49" jamLengthInVehiclesSum="69607" jamLengthInMetersSum="557886.95" meanHaltingDuration="129.52" maxHaltingDuration="266.40" haltingDurationSum="4792.15" meanIntervalHaltingDuration="91.78" maxIntervalHaltingDuration="266.40" intervalHaltingDurationSum="3395.95" startedHalts="27.00" meanVehicleNumber="12.17" maxVehicleNumber="13" />
   <interval begin="7800.00" end="8100.00" id="e2_9" sampledSeconds="1629.36" nVehEntered="8" nVehLeft="20" nVehSeen="20" meanSpeed="0.87" meanTimeLoss="78.43" meanOccupancy="30.66" maxOccupancy="62.05" meanMaxJamLengthInVehicles="4.25" meanMaxJamLengthInMeters="34.47" maxJamLengthInVehicles="12" maxJamLengthInMeters="99.49" jamLengthInVehiclesSum="25625" jamLengthInMetersSum="207695.41" meanHaltingDuration="108.02" maxHaltingDuration="308.80" haltingDurationSum="4429.00" meanIntervalHaltingDuration="31.95" maxIntervalHaltingDuration="144.35" intervalHaltingDurationSum="1309.75" startedHalts="29.00" meanVehicleNumber="5.43" maxVehicleNumber="12" />
   <interval begin="8100.00" end="8400.00" id="e2_9" sampledSeconds="0.00" nVehEntered="0" nVehLeft="0" nVehSeen="0" meanSpeed="-1.00" meanTimeLoss="-1.00" meanOccupancy="0.00" maxOccupancy="0.00" meanMaxJamLengthInVehicles="0.00" meanMaxJamLengthInMeters="0.00" maxJamLengthInVehicles="0" maxJamLengthInMeters="0.00" jamLengthInVehiclesSum="0" jamLengthInMetersSum="0.00" meanHaltingDuration="0.00" maxHaltingDuration="0.00" haltingDurationSum="0.00" meanIntervalHaltingDuration="0.00" maxIntervalHaltingDuration="0.00" intervalHaltingDurationSum="0.00" startedHalts="0.00" meanVehicleNumber="0.00" maxVehicleNumber="0" />
   <interval begin="8400.00" end="8700.00" id="e2_9" sampledSeconds="209.74" nVehEntered="1" nVehLeft="1" nVehSeen="1" meanSpeed="0.14" meanTimeLoss="208.75" meanOccupancy="4.14" maxOccupancy="7.14" meanMaxJamLengthInVehicles="0.68" meanMaxJamLengthInMeters="4.02" maxJamLengthInVehicles="1" maxJamLengthInMeters="5.87" jamLengthInVehiclesSum="4105" jamLengthInMetersSum="24100.46" meanHaltingDuration="0.00" maxHaltingDuration="0.00" haltingDurationSum="0.00" meanIntervalHaltingDuration="0.00" maxIntervalHaltingDuration="0.00" intervalHaltingDurationSum="0.00" startedHalts="1.00" meanVehicleNumber="0.70" maxVehicleNumber="1" />
   <interval begin="8700.00" end="9000.00" id="e2_9" sampledSeconds="0.00" nVehEntered="0" nVehLeft="0" nVehSeen="0" meanSpeed="-1.00" meanTimeLoss="-1.00" meanOccupancy="0.00" maxOccupancy="0.00" meanMaxJamLengthInVehicles="0.00" meanMaxJamLengthInMeters="0.00" maxJamLengthInVehicles="0" maxJamLengthInMeters="0.00" jamLengthInVehiclesSum="0" jamLengthInMetersSum="0.00" meanHaltingDuration="0.00" maxHaltingDuration="0.00" haltingDurationSum="0.00" meanIntervalHaltingDuration="0.00" maxIntervalHaltingDuration="0.00" intervalHaltingDurationSum="0.00" startedHalts="0.00" meanVehicleNumber="0.00" maxVehicleNumber="0" />
   <interval begin="9000.00" end="9300.00" id="e2_9" sampledSeconds="0.00" nVehEntered="0" nVehLeft="0" nVehSeen="0" meanSpeed="-1.00" meanTimeLoss="-1.00" meanOccupancy="0.00" maxOccupancy="0.00" meanMaxJamLengthInVehicles="0.00" meanMaxJamLengthInMeters="0.00" maxJamLengthInVehicles="0" maxJamLengthInMeters="0.00" jamLengthInVehiclesSum="0" jamLengthInMetersSum="0.00" meanHaltingDuration="0.00" maxHaltingDuration="0.00" haltingDurationSum="0.00" meanIntervalHaltingDuration="0.00" maxIntervalHaltingDuration="0.00" intervalHaltingDurationSum="0.00" startedHalts="0.00" meanVehicleNumber="0.00" maxVehicleNumber="0" />
   <interval begin="9300.00" end="9600.00" id="e2_9" sampledSeconds="0.00" nVehEntered="0" nVehLeft="0" nVehSeen="0" meanSpeed="-1.00" meanTimeLoss="-1.00" meanOccupancy="0.00" maxOccupancy="0.00" meanMaxJamLengthInVehicles="0.00" meanMaxJamLengthInMeters="0.00" maxJamLengthInVehicles="0" maxJamLengthInMeters="0.00" jamLengthInVehiclesSum="0" jamLengthInMetersSum="0.00" meanHaltingDuration="0.00" maxHaltingDuration="0.00" haltingDurationSum="0.00" meanIntervalHaltingDuration="0.00" maxIntervalHaltingDuration="0.00" intervalHaltingDurationSum="0.00" startedHalts="0.00" meanVehicleNumber="0.00" maxVehicleNumber="0" />
   <interval begin="9600.00" end="9900.00" id="e2_9" sampledSeconds="0.00" nVehEntered="0" nVehLeft="0" nVehSeen="0" meanSpeed="-1.00" meanTimeLoss="-1.00" meanOccupancy="0.00" maxOccupancy="0.00" meanMaxJamLengthInVehicles="0.00" meanMaxJamLengthInMeters="0.00" maxJamLengthInVehicles="0" maxJamLengthInMeters="0.00" jamLengthInVehiclesSum="0" jamLengthInMetersSum="0.00" meanHaltingDuration="0.00" maxHaltingDuration="0.00" haltingDurationSum="0.00" meanIntervalHaltingDuration="0.00" maxIntervalHaltingDuration="0.00" intervalHaltingDurationSum="0.00" startedHalts="0.00" meanVehicleNumber="0.00" maxVehicleNumber="0" />
   <interval begin="9900.00" end="10200.00" id="e2_9" sampledSeconds="0.00" nVehEntered="0" nVehLeft="0" nVehSeen="0" meanSpeed="-1.00" meanTimeLoss="-1.00" meanOccupancy="0.00" maxOccupancy="0.00" meanMaxJamLengthInVehicles="0.00" meanMaxJamLengthInMeters="0.00" maxJamLengthInVehicles="0" maxJamLengthInMeters="0.00" jamLengthInVehiclesSum="0" jamLengthInMetersSum="0.00" meanHaltingDuration="0.00" maxHaltingDuration="0.00" haltingDurationSum="0.00" meanIntervalHaltingDuration="0.00" maxIntervalHaltingDuration="0.00" intervalHaltingDurationSum="0.00" startedHalts="0.00" meanVehicleNumber="0.00" maxVehicleNumber="0" />
   <interval begin="10200.00" end="10500.00" id="e2_9" sampledSeconds="0.00" nVehEntered="0" nVehLeft="0" nVehSeen="0" meanSpeed="-1.00" meanTimeLoss="-1.00" meanOccupancy="0.00" maxOccupancy="0.00" meanMaxJamLengthInVehicles="0.00" meanMaxJamLengthInMeters="0.00" maxJamLengthInVehicles="0" maxJamLengthInMeters="0.00" jamLengthInVehiclesSum="0" jamLengthInMetersSum="0.00" meanHaltingDuration="0.00" maxHaltingDuration="0.00" haltingDurationSum="0.00" meanIntervalHaltingDuration="0.00" maxIntervalHaltingDuration="0.00" intervalHaltingDurationSum="0.00" startedHalts="0.00" meanVehicleNumber="0.00" maxVehicleNumber="0" />
   <interval begin="10500.00" end="10800.00" id="e2_9" sampledSeconds="0.00" nVehEntered="0" nVehLeft="0" nVehSeen="0" meanSpeed="-1.00" meanTimeLoss="-1.00" meanOccupancy="0.00" maxOccupancy="0.00" meanMaxJamLengthInVehicles="0.00" meanMaxJamLengthInMeters="0.00" maxJamLengthInVehicles="0" maxJamLengthInMeters="0.00" jamLengthInVehiclesSum="0" jamLengthInMetersSum="0.00" meanHaltingDuration="0.00" maxHaltingDuration="0.00" haltingDurationSum="0.00" meanIntervalHaltingDuration="0.00" maxIntervalHaltingDuration="0.00" intervalHaltingDurationSum="0.00" startedHalts="0.00" meanVehicleNumber="0.00" maxVehicleNumber="0" />
   <interval begin="10800.00" end="11100.00" id="e2_9" sampledSeconds="0.00" nVehEntered="0" nVehLeft="0" nVehSeen="0" meanSpeed="-1.00" meanTimeLoss="-1.00" meanOccupancy="0.00" maxOccupancy="0.00" meanMaxJamLengthInVehicles="0.00" meanMaxJamLengthInMeters="0.00" maxJamLengthInVehicles="0" maxJamLengthInMeters="0.00" jamLengthInVehiclesSum="0" jamLengthInMetersSum="0.00" meanHaltingDuration="0.00" maxHaltingDuration="0.00" haltingDurationSum="0.00" meanIntervalHaltingDuration="0.00" maxIntervalHaltingDuration="0.00" intervalHaltingDurationSum="0.00" startedHalts="0.00" meanVehicleNumber="0.00" maxVehicleNumber="0" />
   <interval begin="11100.00" end="11400.00" id="e2_9" sampledSeconds="0.00" nVehEntered="0" nVehLeft="0" nVehSeen="0" meanSpeed="-1.00" meanTimeLoss="-1.00" meanOccupancy="0.00" maxOccupancy="0.00" meanMaxJamLengthInVehicles="0.00" meanMaxJamLengthInMeters="0.00" maxJamLengthInVehicles="0" maxJamLengthInMeters="0.00" jamLengthInVehiclesSum="0" jamLengthInMetersSum="0.00" meanHaltingDuration="0.00" maxHaltingDuration="0.00" haltingDurationSum="0.00" meanIntervalHaltingDuration="0.00" maxIntervalHaltingDuration="0.00" intervalHaltingDurationSum="0.00" startedHalts="0.00" meanVehicleNumber="0.00" maxVehicleNumber="0" />
   <interval begin="11400.00" end="11700.00" id="e2_9" sampledSeconds="0.00" nVehEntered="0" nVehLeft="0" nVehSeen="0" meanSpeed="-1.00" meanTimeLoss="-1.00" meanOccupancy="0.00" maxOccupancy="0.00" meanMaxJamLengthInVehicles="0.00" meanMaxJamLengthInMeters="0.00" maxJamLengthInVehicles="0" maxJamLengthInMeters="0.00" jamLengthInVehiclesSum="0" jamLengthInMetersSum="0.00" meanHaltingDuration="0.00" maxHaltingDuration="0.00" haltingDurationSum="0.00" meanIntervalHaltingDuration="0.00" maxIntervalHaltingDuration="0.00" intervalHaltingDurationSum="0.00" startedHalts="0.00" meanVehicleNumber="0.00" maxVehicleNumber="0" />
   <interval begin="11700.00" end="12000.00" id="e2_9" sampledSeconds="0.00" nVehEntered="0" nVehLeft="0" nVehSeen="0" meanSpeed="-1.00" meanTimeLoss="-1.00" meanOccupancy="0.00" maxOccupancy="0.00" meanMaxJamLengthInVehicles="0.00" meanMaxJamLengthInMeters="0.00" maxJamLengthInVehicles="0" maxJamLengthInMeters="0.00" jamLengthInVehiclesSum="0" jamLengthInMetersSum="0.00" meanHaltingDuration="0.00" maxHaltingDuration="0.00" haltingDurationSum="0.00" meanIntervalHaltingDuration="0.00" maxIntervalHaltingDuration="0.00" intervalHaltingDurationSum="0.00" startedHalts="0.00" meanVehicleNumber="0.00" maxVehicleNumber="0" />
   <interval begin="12000.00" end="12300.00" id="e2_9" sampledSeconds="0.00" nVehEntered="0" nVehLeft="0" nVehSeen="0" meanSpeed="-1.00" meanTimeLoss="-1.00" meanOccupancy="0.00" maxOccupancy="0.00" meanMaxJamLengthInVehicles="0.00" meanMaxJamLengthInMeters="0.00" maxJamLengthInVehicles="0" maxJamLengthInMeters="0.00" jamLengthInVehiclesSum="0" jamLengthInMetersSum="0.00" meanHaltingDuration="0.00" maxHaltingDuration="0.00" haltingDurationSum="0.00" meanIntervalHaltingDuration="0.00" maxIntervalHaltingDuration="0.00" intervalHaltingDurationSum="0.00" startedHalts="0.00" meanVehicleNumber="0.00" maxVehicleNumber="0" />
   <interval begin="12300.00" end="12567.00" id="e2_9" sampledSeconds="0.00" nVehEntered="0" nVehLeft="0" nVehSeen="0" meanSpeed="-1.00" meanTimeLoss="-1.00" meanOccupancy="0.00" maxOccupancy="0.00" meanMaxJamLengthInVehicles="0.00" meanMaxJamLengthInMeters="0.00" maxJamLengthInVehicles="0" maxJamLengthInMeters="0.00" jamLengthInVehiclesSum="0" jamLengthInMetersSum="0.00" meanHaltingDuration="0.00" maxHaltingDuration="0.00" haltingDurationSum="0.00" meanIntervalHaltingDuration="0.00" maxIntervalHaltingDuration="0.00" intervalHaltingDurationSum="0.00" startedHalts="0.00" meanVehicleNumber="0.00" maxVehicleNumber="0" />
</detector>
